acceso_zk/__init__.py
acceso_zk/client.py
acceso_zk/types.py
acceso_zk-1.0.0.dist-info/licenses/LICENSE
acceso_zk-1.0.0.dist-info/METADATA
acceso_zk-1.0.0.dist-info/WHEEL
acceso_zk-1.0.0.dist-info/top_level.txt
acceso_zk-1.0.0.dist-info/RECORD
